design.plone.ctgeneric-1.0.6-py3.8-nspkg.pth
design/plone/ctgeneric/__init__.py
design/plone/ctgeneric/configure.zcml
design/plone/ctgeneric/indexers.py
design/plone/ctgeneric/monkey.py
design/plone/ctgeneric/monkey.zcml
design/plone/ctgeneric/permissions.zcml
design/plone/ctgeneric/setuphandlers.py
design/plone/ctgeneric/testing.py
design/plone/ctgeneric/utils.py
design/plone/ctgeneric/adapters/__init__.py
design/plone/ctgeneric/adapters/configure.zcml
design/plone/ctgeneric/adapters/schema_tweaks.py
design/plone/ctgeneric/behaviors/__init__.py
design/plone/ctgeneric/behaviors/address.py
design/plone/ctgeneric/behaviors/configure.zcml
design/plone/ctgeneric/behaviors/contatti.py
design/plone/ctgeneric/behaviors/documento.py
design/plone/ctgeneric/behaviors/evento.py
design/plone/ctgeneric/behaviors/luogo.py
design/plone/ctgeneric/behaviors/news.py
design/plone/ctgeneric/behaviors/persona.py
design/plone/ctgeneric/behaviors/servizio.py
design/plone/ctgeneric/behaviors/uo.py
design/plone/ctgeneric/browser/__init__.py
design/plone/ctgeneric/browser/configure.zcml
design/plone/ctgeneric/browser/controlpanel.py
design/plone/ctgeneric/browser/static/.gitkeep
design/plone/ctgeneric/interfaces/__init__.py
design/plone/ctgeneric/interfaces/layer.py
design/plone/ctgeneric/interfaces/settings.py
design/plone/ctgeneric/locales/README.rst
design/plone/ctgeneric/locales/__init__.py
design/plone/ctgeneric/locales/design.plone.ctgeneric.pot
design/plone/ctgeneric/locales/update.py
design/plone/ctgeneric/locales/update.sh
design/plone/ctgeneric/locales/en/LC_MESSAGES/design.plone.ctgeneric.po
design/plone/ctgeneric/profiles/default/browserlayer.xml
design/plone/ctgeneric/profiles/default/catalog.xml
design/plone/ctgeneric/profiles/default/controlpanel.xml
design/plone/ctgeneric/profiles/default/metadata.xml
design/plone/ctgeneric/profiles/default/rolemap.xml
design/plone/ctgeneric/profiles/default/types.xml
design/plone/ctgeneric/profiles/default/registry/criteria.xml
design.plone.ctgeneric-1.0.6.dist-info/LICENSE.GPL
design.plone.ctgeneric-1.0.6.dist-info/LICENSE.rst
design.plone.ctgeneric-1.0.6.dist-info/METADATA
design.plone.ctgeneric-1.0.6.dist-info/WHEEL
design.plone.ctgeneric-1.0.6.dist-info/entry_points.txt
design.plone.ctgeneric-1.0.6.dist-info/namespace_packages.txt
design.plone.ctgeneric-1.0.6.dist-info/top_level.txt
design.plone.ctgeneric-1.0.6.dist-info/RECORD
